questionflow/__init__.py
questionflow/question_flow.py
questionflow/classes/__init__.py
questionflow/classes/answer.py
questionflow/classes/multiple_answer_question.py
questionflow/classes/multiple_choice_question.py
questionflow/classes/question.py
questionflow/classes/yes_no_question.py
questionflow-0.2.2.dist-info/LICENSE
questionflow-0.2.2.dist-info/METADATA
questionflow-0.2.2.dist-info/WHEEL
questionflow-0.2.2.dist-info/top_level.txt
questionflow-0.2.2.dist-info/RECORD
